victims/__init__.py
victims/web/__init__.py
victims/web/__main__.py
victims/web/application.py
victims/web/cache.py
victims/web/config.py
victims/web/errors.py
victims/web/models.py
victims/web/submissions.py
victims/web/user.py
victims/web/util.py
victims/web/admin/__init__.py
victims/web/blueprints/__init__.py
victims/web/blueprints/auth/__init__.py
victims/web/blueprints/service_v1/__init__.py
victims/web/blueprints/service_v2/__init__.py
victims/web/blueprints/ui/__init__.py
victims/web/blueprints/ui/static/jquery.js
victims/web/blueprints/ui/static/robots.txt
victims/web/blueprints/ui/static/css/style.css
victims/web/blueprints/ui/static/images/victims-button.png
victims/web/blueprints/ui/templates/about.html
victims/web/blueprints/ui/templates/bugs.html
victims/web/blueprints/ui/templates/client.html
victims/web/blueprints/ui/templates/hashes.html
victims/web/blueprints/ui/templates/index.html
victims/web/blueprints/ui/templates/onehash.html
victims/web/blueprints/ui/templates/search.html
victims/web/blueprints/ui/templates/submit_artifact.html
victims/web/handlers/__init__.py
victims/web/handlers/forms.py
victims/web/handlers/security.py
victims/web/handlers/sslify.py
victims/web/handlers/task.py
victims/web/plugin/__init__.py
victims/web/plugin/charon.py
victims/web/plugin/crosstalk.py
victims/web/plugin/downloader.py
victims/web/plugin/github.py
victims/web/plugin/maven.py
victims/web/plugin/rubysec.py
victims/web/static/css/victims.css
victims/web/templates/base.html
victims/web/templates/error.html
victims/web/templates/evd_base.html
victims/web/templates/util.html
victims/web/templates/admin/cache_index.html
victims/web/templates/admin/master.html
victims/web/templates/admin/file/edit.html
victims/web/templates/admin/file/form.html
victims/web/templates/admin/file/list.html
victims/web/templates/admin/file/rename.html
victims_web-2.2.1.dist-info/DESCRIPTION.rst
victims_web-2.2.1.dist-info/METADATA
victims_web-2.2.1.dist-info/RECORD
victims_web-2.2.1.dist-info/WHEEL
victims_web-2.2.1.dist-info/entry_points.txt
victims_web-2.2.1.dist-info/metadata.json
victims_web-2.2.1.dist-info/top_level.txt
