Metadata-Version: 2.0
Name: victims-web
Version: 2.2.1
Summary: Victims Web Service
Home-page: http://victi.ms
Author: Steve Milner
Author-email: UNKNOWN
License: AGPLv3
Platform: UNKNOWN
Classifier: License :: OSI Approved :: GNU Affero General Public License v3
Classifier: Operating System :: OS Independent
Classifier: Programming Language :: Python
Classifier: Framework :: Flask
Classifier: Intended Audience :: Developers
Classifier: Intended Audience :: System Administrators
Classifier: Topic :: Internet :: WWW/HTTP :: WSGI :: Server
Classifier: Topic :: Security
Requires-Dist: Flask (>=0.10)
Requires-Dist: Flask-Admin (>=1.0.7)
Requires-Dist: Flask-Bcrypt
Requires-Dist: Flask-Bootstrap
Requires-Dist: Flask-Cache
Requires-Dist: Flask-Login (==0.2.11)
Requires-Dist: Flask-MongoEngine (==0.7.0)
Requires-Dist: Flask-Reggie
Requires-Dist: Flask-SSLify
Requires-Dist: Flask-SeaSurf
Requires-Dist: Flask-Views
Requires-Dist: Flask-WTF (>=0.9.1)
Requires-Dist: PyYAML
Requires-Dist: blinker
Requires-Dist: mongoengine (==0.8.4)
Requires-Dist: pymongo (==2.6.2)
Requires-Dist: raven[flask]
Requires-Dist: requests
